char_range/__init__.py
char_range/char_range.py
char_range-0.0.2.dist-info/LICENSE
char_range-0.0.2.dist-info/METADATA
char_range-0.0.2.dist-info/WHEEL
char_range-0.0.2.dist-info/top_level.txt
char_range-0.0.2.dist-info/RECORD
