Metadata-Version: 2.1
Name: char-range
Version: 0.0.2
Summary: Generates an iterator for characters from `start` to `end`, inclusive
Author-email: Brendan Innes <binnes22@gmail.com>
Classifier: Programming Language :: Python :: 3
Classifier: License :: OSI Approved :: MIT License
Classifier: Operating System :: OS Independent
Requires-Python: >=3.7
License-File: LICENSE
